openg2p_fastapi_common/__init__.py
openg2p_fastapi_common/app.py
openg2p_fastapi_common/component.py
openg2p_fastapi_common/config.py
openg2p_fastapi_common/context.py
openg2p_fastapi_common/controller.py
openg2p_fastapi_common/exception.py
openg2p_fastapi_common/models.py
openg2p_fastapi_common/ping.py
openg2p_fastapi_common/schemas.py
openg2p_fastapi_common/service.py
openg2p_fastapi_common/errors/__init__.py
openg2p_fastapi_common/errors/base_error.py
openg2p_fastapi_common/errors/base_exception.py
openg2p_fastapi_common/errors/http_exceptions.py
openg2p_fastapi_common/utils/__init__.py
openg2p_fastapi_common/utils/cookie_utils.py
openg2p_fastapi_common/utils/crypto.py
openg2p_fastapi_common/utils/ctx_thread.py
openg2p_fastapi_common/utils/holder.py
openg2p_fastapi_common/utils/string_utils.py
openg2p_fastapi_common-1.1.4.dist-info/METADATA
openg2p_fastapi_common-1.1.4.dist-info/WHEEL
openg2p_fastapi_common-1.1.4.dist-info/licenses/LICENSE
openg2p_fastapi_common-1.1.4.dist-info/RECORD
